
{
  "indexes": [
    {
      "collectionGroup": "orders",
      "queryScope": "COLLECTION",
      "fields": [
        { "fieldPath": "classification_status", "order": "ASCENDING" },
        { "fieldPath": "projectId", "order": "ASCENDING" },
        { "fieldPath": "__name__", "order": "ASCENDING" }
      ]
    },
    {
      "collectionGroup": "orders",
      "queryScope": "COLLECTION",
      "fields": [
        { "fieldPath": "disciplina_normalizada", "order": "ASCENDING" },
        { "fieldPath": "projectId", "order": "ASCENDING" },
        { "fieldPath": "__name__", "order": "ASCENDING" }
      ]
    },
    {
      "collectionGroup": "orders",
      "queryScope": "COLLECTION",
      "fields": [
        { "fieldPath": "disciplina_normalizada", "order": "ASCENDING" },
        { "fieldPath": "subcausa_normalizada", "order": "ASCENDING" },
        { "fieldPath": "projectId", "order": "ASCENDING" },
        { "fieldPath": "__name__", "order": "ASCENDING" }
      ]
    }
  ],
  "fieldOverrides": [
    {
      "collectionGroup": "aggregates",
      "fieldPath": "disciplines",
      "indexes": []
    },
    {
      "collectionGroup": "aggregates",
      "fieldPath": "rootCauses",
      "indexes": []
    },
    {
      "collectionGroup": "aggregates",
      "fieldPath": "formats",
      "indexes": []
    }
  ]
}
